curviriver/__init__.py
curviriver/curvilinear.py
curviriver/exceptions.py
curviriver/interpolation.py
curviriver/py.typed
curviriver/smoothing.py
curviriver-0.1.0.dist-info/LICENSE
curviriver-0.1.0.dist-info/METADATA
curviriver-0.1.0.dist-info/WHEEL
curviriver-0.1.0.dist-info/top_level.txt
curviriver-0.1.0.dist-info/RECORD
